[
  {
    "name": "Kaleb",
    "wins": 208,
    "losses": 181,
    "winPercentage": "0.535",
    "rank": 1
  },
  {
    "name": "Tyler",
    "wins": 206,
    "losses": 184,
    "winPercentage": "0.528",
    "rank": 2
  },
  {
    "name": "Chris",
    "wins": 154,
    "losses": 139,
    "winPercentage": "0.526",
    "rank": 3
  },
  {
    "name": "Pat",
    "wins": 203,
    "losses": 188,
    "winPercentage": "0.519",
    "rank": 4
  },
  {
    "name": "Terry",
    "wins": 205,
    "losses": 190,
    "winPercentage": "0.519",
    "rank": 5
  },
  {
    "name": "Clay",
    "wins": 196,
    "losses": 192,
    "winPercentage": "0.505",
    "rank": 6
  },
  {
    "name": "Zack",
    "wins": 195,
    "losses": 193,
    "winPercentage": "0.503",
    "rank": 7
  }
]